Metadata-Version: 2.1
Name: blendplot
Version: 1.0.0
Summary: A program for plotting 3D scatter plots for use in Blender
Home-page: https://github.com/ExcaliburZero/blender-astro-visualization
Author: Christopher Wells
Author-email: cwellsny@nycap.rr.com
License: MIT
Platform: UNKNOWN
Classifier: Programming Language :: Python
Classifier: Programming Language :: Python :: 3
Classifier: Operating System :: OS Independent
Classifier: License :: OSI Approved :: MIT License
